{
    "shop_1": [
        {
            "cost": [
                {
                    "count": 10,
                    "id": 30301
                }
            ],
            "id": 1,
            "items": [
                {
                    "count": 10,
                    "id": 10102
                }
            ],
            "sort_id": 1
        },
        {
            "cost": [
                {
                    "count": 10,
                    "id": 30301
                }
            ],
            "id": 2,
            "items": [
                {
                    "count": 10,
                    "id": 10102
                }
            ],
            "sort_id": 2
        },
        {
            "cost": [
                {
                    "count": 10,
                    "id": 30301
                }
            ],
            "id": 3,
            "items": [
                {
                    "count": 10,
                    "id": 10102
                }
            ],
            "sort_id": 2
        },
        {
            "cost": [
                {
                    "count": 10,
                    "id": 30301
                }
            ],
            "id": 4,
            "items": [
                {
                    "count": 10,
                    "id": 10102
                }
            ],
            "sort_id": 3
        },
        {
            "id": 5,
            "items": [
                {
                    "count": 10,
                    "id": 10102
                }
            ],
            "limit_day": 1,
            "sort_id": 3
        }
    ],
    "shop_2": [
        {
            "cost": [
                {
                    "count": 10,
                    "id": 30301
                }
            ],
            "id": 1,
            "items": [
                {
                    "count": 10,
                    "id": 10102
                }
            ],
            "sort_id": 1
        },
        {
            "cost": [
                {
                    "count": 10,
                    "id": 30301
                }
            ],
            "id": 2,
            "items": [
                {
                    "count": 10,
                    "id": 10102
                }
            ],
            "sort_id": 2
        },
        {
            "cost": [
                {
                    "count": 10,
                    "id": 30301
                }
            ],
            "id": 3,
            "items": [
                {
                    "count": 10,
                    "id": 10102
                }
            ],
            "sort_id": 2
        },
        {
            "cost": [
                {
                    "count": 10,
                    "id": 30301
                }
            ],
            "id": 4,
            "items": [
                {
                    "count": 10,
                    "id": 10102
                }
            ],
            "sort_id": 3
        },
        {
            "id": 5,
            "items": [
                {
                    "count": 10,
                    "id": 10102
                }
            ],
            "limit_day": 1,
            "sort_id": 3
        }
    ],
    "shop_config": [
        {
            "id": 1,
            "type": 1
        },
        {
            "id": 2,
            "refresh_hour": 24,
            "type": 2
        }
    ]
}